pycareer/__init__.py
pycareer/cli.py
pycareer/formatter.py
pycareer/models.py
pycareer/request.py
pycareer-0.1.6.dist-info/METADATA
pycareer-0.1.6.dist-info/WHEEL
pycareer-0.1.6.dist-info/entry_points.txt
pycareer-0.1.6.dist-info/RECORD
